autoneo/__init__.py
autoneo/builder.py
autoneo/exporter.py
autoneo/query_builder.py
tests/__init__.py
tests/test_builder.py
autoneo-0.0.2.dist-info/LICENSE
autoneo-0.0.2.dist-info/METADATA
autoneo-0.0.2.dist-info/WHEEL
autoneo-0.0.2.dist-info/top_level.txt
autoneo-0.0.2.dist-info/RECORD
