Metadata-Version: 2.1
Name: autoneo
Version: 0.0.2
Summary: A simple tool for building graph databases from multiple relational sources.
Home-page: https://github.com/raghavp96/autoneo
Author: Raghavprasanna Rajagopalan
Author-email: raghavp96@gmail.com
License: UNKNOWN
Platform: UNKNOWN
Classifier: Programming Language :: Python :: 3
Classifier: License :: OSI Approved :: MIT License
Classifier: Operating System :: OS Independent
Requires-Python: >=3.7
Requires-Dist: neo4j (>=4.1.0)
